odoo/addons/stock_location_release_channel_restriction/README.rst
odoo/addons/stock_location_release_channel_restriction/__init__.py
odoo/addons/stock_location_release_channel_restriction/__manifest__.py
odoo/addons/stock_location_release_channel_restriction/i18n/fr.po
odoo/addons/stock_location_release_channel_restriction/i18n/it.po
odoo/addons/stock_location_release_channel_restriction/i18n/stock_location_release_channel_restriction.pot
odoo/addons/stock_location_release_channel_restriction/models/__init__.py
odoo/addons/stock_location_release_channel_restriction/models/exception.py
odoo/addons/stock_location_release_channel_restriction/models/stock_location.py
odoo/addons/stock_location_release_channel_restriction/models/stock_move_line.py
odoo/addons/stock_location_release_channel_restriction/readme/CONFIGURE.md
odoo/addons/stock_location_release_channel_restriction/readme/CONTEXT.md
odoo/addons/stock_location_release_channel_restriction/readme/CONTRIBUTORS.md
odoo/addons/stock_location_release_channel_restriction/readme/DESCRIPTION.md
odoo/addons/stock_location_release_channel_restriction/readme/USAGE.md
odoo/addons/stock_location_release_channel_restriction/static/description/icon.png
odoo/addons/stock_location_release_channel_restriction/static/description/index.html
odoo/addons/stock_location_release_channel_restriction/tests/__init__.py
odoo/addons/stock_location_release_channel_restriction/tests/test_release_channel_restriction.py
odoo/addons/stock_location_release_channel_restriction/views/stock_location.xml
odoo_addon_stock_location_release_channel_restriction-16.0.1.1.1.dist-info/METADATA
odoo_addon_stock_location_release_channel_restriction-16.0.1.1.1.dist-info/WHEEL
odoo_addon_stock_location_release_channel_restriction-16.0.1.1.1.dist-info/top_level.txt
odoo_addon_stock_location_release_channel_restriction-16.0.1.1.1.dist-info/RECORD
