Metadata-Version: 2.1
Name: odoo-addon-stock_location_release_channel_restriction
Version: 16.0.1.1.1
Summary: This module allows to restrict location content to products that are in the same release channel (moves).
Home-page: https://github.com/OCA/stock-logistics-warehouse
Author: ACSONE SA/NV,Odoo Community Association (OCA)
Author-email: support@odoo-community.org
License: AGPL-3
Classifier: Programming Language :: Python
Classifier: Framework :: Odoo
Classifier: Framework :: Odoo :: 16.0
Classifier: License :: OSI Approved :: GNU Affero General Public License v3
Requires-Python: >=3.10
Requires-Dist: odoo-addon-stock-location-pending-move<16.1dev,>=16.0dev
Requires-Dist: odoo-addon-stock-release-channel<16.1dev,>=16.0dev
Requires-Dist: odoo<16.1dev,>=16.0a
